neura_library-0.6.0.dist-info/licenses/LICENSE
neuralib/__init__.py
neuralib/atlas/__init__.py
neuralib/atlas/data.py
neuralib/atlas/map.py
neuralib/atlas/plot.py
neuralib/atlas/typing.py
neuralib/atlas/util.py
neuralib/atlas/view.py
neuralib/atlas/brainrender/__init__.py
neuralib/atlas/brainrender/core.py
neuralib/atlas/brainrender/main_app.py
neuralib/atlas/brainrender/probe.py
neuralib/atlas/brainrender/roi.py
neuralib/atlas/brainrender/util.py
neuralib/atlas/ccf/__init__.py
neuralib/atlas/ccf/dataframe.py
neuralib/atlas/ccf/matrix.py
neuralib/atlas/cellatlas/__init__.py
neuralib/atlas/cellatlas/core.py
neuralib/dashboard/__init__.py
neuralib/dashboard/base.py
neuralib/dashboard/example.py
neuralib/dashboard/example_multi.py
neuralib/dashboard/tool.py
neuralib/dashboard/util.py
neuralib/dashboard/view_brain.py
neuralib/dashboard/examples/__init__.py
neuralib/dashboard/examples/__main__.py
neuralib/dashboard/examples/model.py
neuralib/dashboard/examples/view_all.py
neuralib/dashboard/examples/view_animal.py
neuralib/dashboard/examples/view_figure.py
neuralib/imaging/__init__.py
neuralib/imaging/registration/__init__.py
neuralib/imaging/registration/coordinates.py
neuralib/imaging/scanbox/__init__.py
neuralib/imaging/scanbox/core.py
neuralib/imaging/scanbox/view.py
neuralib/imaging/spikes/__init__.py
neuralib/imaging/spikes/cascade.py
neuralib/imaging/spikes/oasis.py
neuralib/imaging/suite2p/__init__.py
neuralib/imaging/suite2p/core.py
neuralib/imaging/suite2p/plot.py
neuralib/imaging/suite2p/signals.py
neuralib/imaging/widefield/__init__.py
neuralib/imaging/widefield/align.py
neuralib/imaging/widefield/fft.py
neuralib/imaging/widefield/fft_view.py
neuralib/imaging/widefield/main_app.py
neuralib/imaging/widefield/plot.py
neuralib/imaging/widefield/svd.py
neuralib/imglib/__init__.py
neuralib/imglib/array.py
neuralib/imglib/color.py
neuralib/imglib/io.py
neuralib/imglib/labeller.py
neuralib/imglib/norm.py
neuralib/imglib/transform.py
neuralib/io/__init__.py
neuralib/io/core.py
neuralib/io/csv_header.py
neura_library-0.6.0.dist-info/METADATA
neura_library-0.6.0.dist-info/WHEEL
neura_library-0.6.0.dist-info/entry_points.txt
neura_library-0.6.0.dist-info/top_level.txt
neura_library-0.6.0.dist-info/RECORD
