Metadata-Version: 2.4
Name: neura-library
Version: 0.6.0
Summary: Utility tools for system neuroscience research, including Open Source Wrapper or Parser
Author-email: Yu-Ting Wei <ytsimon2004@gmail.com>, Ta-Shun Su <antoniost29@gmail.com>
License: BSD 3-Clause License
Project-URL: Homepage, https://github.com/ytsimon2004/neuralib
Project-URL: Documentation, https://neuralib.readthedocs.io/en/latest/index.html
Project-URL: Repository, https://github.com/ytsimon2004/neuralib
Project-URL: Issues, https://github.com/ytsimon2004/neuralib/issues
Keywords: Neuroscience,visual neuroscience,cellular imaging,brain mapping,spatial navigation
Classifier: Programming Language :: Python :: 3.11
Classifier: Programming Language :: Python :: 3.12
Classifier: License :: OSI Approved :: BSD License
Classifier: Natural Language :: English
Classifier: Operating System :: OS Independent
Classifier: Topic :: Scientific/Engineering
Classifier: Intended Audience :: Science/Research
Classifier: Typing :: Typed
Requires-Python: <3.13,>=3.11
License-File: LICENSE
Requires-Dist: attrs>=25.3.0
Requires-Dist: argclz>=1.0.0
Requires-Dist: colorama>=0.4.6
Requires-Dist: colorlog>=6.9.0
Requires-Dist: matplotlib>=3.10.3
Requires-Dist: matplotlib_venn>=1.1.2
Requires-Dist: seaborn>=0.13.2
Requires-Dist: numpy
Requires-Dist: scipy>=1.15.3
Requires-Dist: scikit-image>=0.25.2
Requires-Dist: pandas
Requires-Dist: polars
Requires-Dist: pyarrow
Requires-Dist: tifffile
Requires-Dist: opencv-python>=4.8.0.76
Requires-Dist: tqdm
Requires-Dist: requests
Requires-Dist: gdown
Requires-Dist: rich
Requires-Dist: h5py
Requires-Dist: typing_extensions
Provides-Extra: atlas
Requires-Dist: brainrender; extra == "atlas"
Requires-Dist: pynrrd; extra == "atlas"
Requires-Dist: openpyxl; extra == "atlas"
Requires-Dist: anytree; extra == "atlas"
Requires-Dist: plotly; extra == "atlas"
Requires-Dist: fastexcel; extra == "atlas"
Provides-Extra: scan
Requires-Dist: xmltodict; extra == "scan"
Requires-Dist: aicspylibczi; extra == "scan"
Provides-Extra: imaging
Requires-Dist: sbxreader; extra == "imaging"
Requires-Dist: ruamel.yaml; extra == "imaging"
Requires-Dist: numba; extra == "imaging"
Requires-Dist: bokeh; extra == "imaging"
Requires-Dist: napari; extra == "imaging"
Provides-Extra: imglib
Requires-Dist: pdf2image; extra == "imglib"
Requires-Dist: imageio; extra == "imglib"
Provides-Extra: rastermap
Requires-Dist: rastermap; extra == "rastermap"
Provides-Extra: cascade
Requires-Dist: tensorflow; extra == "cascade"
Provides-Extra: segmentation
Requires-Dist: pyqt6; extra == "segmentation"
Requires-Dist: pyqtgraph; extra == "segmentation"
Requires-Dist: csbdeep; extra == "segmentation"
Requires-Dist: roifile; extra == "segmentation"
Requires-Dist: napari; extra == "segmentation"
Provides-Extra: stardist
Requires-Dist: neura-library[segmentation]; extra == "stardist"
Requires-Dist: stardist; extra == "stardist"
Requires-Dist: tensorflow; extra == "stardist"
Requires-Dist: numpy<2.0; extra == "stardist" and extra == "stardist"
Provides-Extra: opt
Requires-Dist: slackclient; extra == "opt"
Requires-Dist: gspread; extra == "opt"
Requires-Dist: psutil; extra == "opt"
Provides-Extra: all
Requires-Dist: neura-library[atlas]; extra == "all"
Requires-Dist: neura-library[scan]; extra == "all"
Requires-Dist: neura-library[imaging]; extra == "all"
Requires-Dist: neura-library[imglib]; extra == "all"
Requires-Dist: neura-library[rastermap]; extra == "all"
Requires-Dist: neura-library[opt]; extra == "all"
Provides-Extra: dev
Requires-Dist: neura-library[all]; extra == "dev"
Requires-Dist: neura-library[stardist]; extra == "dev"
Requires-Dist: pre-commit; extra == "dev"
Requires-Dist: ruff; extra == "dev"
Requires-Dist: pytest; extra == "dev"
Requires-Dist: pytest-cov; extra == "dev"
Provides-Extra: doc
Requires-Dist: neura-library[all]; extra == "doc"
Requires-Dist: neura-library[cascade]; extra == "doc"
Requires-Dist: sphinx; extra == "doc"
Requires-Dist: nbsphinx; extra == "doc"
Requires-Dist: sphinx-toolbox; extra == "doc"
Requires-Dist: sphinx-rtd-theme; extra == "doc"
Requires-Dist: sphinx-prompt; extra == "doc"
Requires-Dist: sphinx_copybutton; extra == "doc"
Dynamic: license-file
